testyoke/__init__.py
testyoke/__main__.py
testyoke/view.py
testyoke/analytics/__init__.py
testyoke/analytics/mem.py
testyoke/analytics/sha.py
testyoke/api/__init__.py
testyoke/cli/__init__.py
testyoke/client/__init__.py
testyoke/client/__main__.py
testyoke/cvs/__init__.py
testyoke/cvs/git.py
testyoke/formats/__init__.py
testyoke/formats/xml/__init__.py
testyoke/formats/xml/junit.py
testyoke/localconfig/__init__.py
testyoke/models/__init__.py
testyoke/persist/__init__.py
testyoke/persist/file.py
testyoke/server/__init__.py
testyoke/server/__main__.py
testyoke/version/__init__.py
testyoke-0.2.6.dist-info/METADATA
testyoke-0.2.6.dist-info/WHEEL
testyoke-0.2.6.dist-info/entry_points.txt
testyoke-0.2.6.dist-info/top_level.txt
testyoke-0.2.6.dist-info/RECORD
