Metadata-Version: 2.1
Name: testyoke
Version: 0.2.6
Summary: Provide insights on the outcomes of software test cases.
Home-page: https://github.com/trevorgrayson/testyoke
Author: trevor grayson
Author-email: trevor@ipsumllc.com
License: UNKNOWN
Platform: UNKNOWN
Classifier: Programming Language :: Python :: 3
Requires-Python: >=3.6
Provides-Extra: server
Requires-Dist: flask (>=1.1.1) ; extra == 'server'
